gitlab_branch/__init__.py
gitlab_branch/__version__.py
gitlab_branch/utils.py
gitlab_branch-0.1.dist-info/LICENSE
gitlab_branch-0.1.dist-info/METADATA
gitlab_branch-0.1.dist-info/WHEEL
gitlab_branch-0.1.dist-info/entry_points.txt
gitlab_branch-0.1.dist-info/top_level.txt
gitlab_branch-0.1.dist-info/RECORD
