Metadata-Version: 2.1
Name: gitlab-branch
Version: 0.1
Summary: Manage branch for gitlab project
Home-page: https://github.com/joelee2012/gitlab-branch
Author: Joe Lee
Author-email: lj_2005@163.com
License: Apache 2.0
Project-URL: Documentation, https://gitlab-branch.readthedocs.io
Project-URL: Source, https://github.com/joelee2012/gitlab-branch
Keywords: branch,gitlab
Platform: UNKNOWN
Classifier: Development Status :: 5 - Production/Stable
Classifier: Intended Audience :: Developers
Classifier: Intended Audience :: System Administrators
Classifier: License :: OSI Approved :: Apache Software License
Classifier: Operating System :: OS Independent
Classifier: Programming Language :: Python
Classifier: Programming Language :: Python :: 3
Classifier: Programming Language :: Python :: 3.6
Classifier: Programming Language :: Python :: 3.7
Classifier: Programming Language :: Python :: 3.8
Classifier: Programming Language :: Python :: 3.9
Classifier: Programming Language :: Python :: 3.10
Classifier: Topic :: Software Development
Requires-Python: >=3.6
License-File: LICENSE
Requires-Dist: python-gitlab
